ct_neat_python-1.0.1.dist-info/licenses/LICENSE.txt
ctneat/__init__.py
ctneat/activations.py
ctneat/aggregations.py
ctneat/attributes.py
ctneat/checkpoint.py
ctneat/config.py
ctneat/discretizer.py
ctneat/distributed.py
ctneat/genes.py
ctneat/genome.py
ctneat/graphs.py
ctneat/math_util.py
ctneat/parallel.py
ctneat/population.py
ctneat/reporting.py
ctneat/reproduction.py
ctneat/species.py
ctneat/stagnation.py
ctneat/statistics.py
ctneat/threaded.py
ctneat/api/iznn_api.py
ctneat/ctrnn/__init__.py
ctneat/ctrnn/ctrnn_visualize.py
ctneat/iznn/__init__.py
ctneat/iznn/auxillary_funcs.py
ctneat/iznn/dynamic_attractors.py
ctneat/nn/__init__.py
ctneat/nn/feed_forward.py
ctneat/nn/recurrent.py
ct_neat_python-1.0.1.dist-info/METADATA
ct_neat_python-1.0.1.dist-info/WHEEL
ct_neat_python-1.0.1.dist-info/top_level.txt
ct_neat_python-1.0.1.dist-info/RECORD
