Metadata-Version: 2.4
Name: ct-neat-python
Version: 1.0.1
Summary: A CT (Continuous Time) NEAT (NeuroEvolution of Augmenting Topologies) implementation
Author-email: Sergiy Horef <s@unzim.com>
Maintainer-email: Sergiy Horef <s@unzim.com>
License-Expression: BSD-3-Clause
Project-URL: Homepage, https://github.com/Horef/ct-neat-python
Project-URL: Repository, https://github.com/Horef/ct-neat-python
Project-URL: Documentation, https://ct-neat-python.readthedocs.io
Keywords: neat,ctrnn,iznn,neuroevolution,evolutionary algorithms,genetic algorithms,machine learning,artificial intelligence,ai
Classifier: Development Status :: 5 - Production/Stable
Classifier: Intended Audience :: Developers
Classifier: Intended Audience :: Education
Classifier: Intended Audience :: Science/Research
Classifier: Operating System :: OS Independent
Classifier: Programming Language :: Python :: 3.8
Classifier: Programming Language :: Python :: 3.9
Classifier: Programming Language :: Python :: 3.10
Classifier: Programming Language :: Python :: 3.11
Classifier: Programming Language :: Python :: 3.12
Classifier: Programming Language :: Python :: Implementation :: PyPy
Classifier: Topic :: Scientific/Engineering
Requires-Python: >=3.8
License-File: LICENSE.txt
Requires-Dist: numpy
Requires-Dist: scipy
Requires-Dist: joblib
Requires-Dist: matplotlib
Requires-Dist: scikit-learn
Requires-Dist: graphviz
Requires-Dist: pyrqa
Dynamic: license-file
